LICENSE
README.md
pyproject.toml
setup.py
diagrams_xtd/__init__.py
diagrams_xtd/cli.py
diagrams_xtd.egg-info/PKG-INFO
diagrams_xtd.egg-info/SOURCES.txt
diagrams_xtd.egg-info/dependency_links.txt
diagrams_xtd.egg-info/not-zip-safe
diagrams_xtd.egg-info/top_level.txt
diagrams_xtd/alibabacloud/__init__.py
diagrams_xtd/alibabacloud/analytics.py
diagrams_xtd/alibabacloud/application.py
diagrams_xtd/alibabacloud/communication.py
diagrams_xtd/alibabacloud/compute.py
diagrams_xtd/alibabacloud/database.py
diagrams_xtd/alibabacloud/iot.py
diagrams_xtd/alibabacloud/network.py
diagrams_xtd/alibabacloud/security.py
diagrams_xtd/alibabacloud/storage.py
diagrams_xtd/alibabacloud/web.py
diagrams_xtd/aws/__init__.py
diagrams_xtd/aws/analytics.py
diagrams_xtd/aws/ar.py
diagrams_xtd/aws/blockchain.py
diagrams_xtd/aws/business.py
diagrams_xtd/aws/cluster.py
diagrams_xtd/aws/compute.py
diagrams_xtd/aws/cost.py
diagrams_xtd/aws/database.py
diagrams_xtd/aws/devtools.py
diagrams_xtd/aws/enablement.py
diagrams_xtd/aws/enduser.py
diagrams_xtd/aws/engagement.py
diagrams_xtd/aws/game.py
diagrams_xtd/aws/general.py
diagrams_xtd/aws/integration.py
diagrams_xtd/aws/iot.py
diagrams_xtd/aws/management.py
diagrams_xtd/aws/media.py
diagrams_xtd/aws/migration.py
diagrams_xtd/aws/ml.py
diagrams_xtd/aws/mobile.py
diagrams_xtd/aws/network.py
diagrams_xtd/aws/quantum.py
diagrams_xtd/aws/robotics.py
diagrams_xtd/aws/satellite.py
diagrams_xtd/aws/security.py
diagrams_xtd/aws/storage.py
diagrams_xtd/azure/__init__.py
diagrams_xtd/azure/analytics.py
diagrams_xtd/azure/cluster.py
diagrams_xtd/azure/compute.py
diagrams_xtd/azure/database.py
diagrams_xtd/azure/devops.py
diagrams_xtd/azure/general.py
diagrams_xtd/azure/identity.py
diagrams_xtd/azure/integration.py
diagrams_xtd/azure/iot.py
diagrams_xtd/azure/migration.py
diagrams_xtd/azure/ml.py
diagrams_xtd/azure/mobile.py
diagrams_xtd/azure/network.py
diagrams_xtd/azure/security.py
diagrams_xtd/azure/storage.py
diagrams_xtd/azure/web.py
diagrams_xtd/base/__init__.py
diagrams_xtd/c4/__init__.py
diagrams_xtd/custom/__init__.py
diagrams_xtd/digitalocean/__init__.py
diagrams_xtd/digitalocean/compute.py
diagrams_xtd/digitalocean/database.py
