Metadata-Version: 2.1
Name: diagrams-xtd
Version: 0.23.4.14
Summary: Extended version of diagrams
Home-page: https://github.com/diagrams-web/diagrams-xtd
Author: ['Diagrams-web <no_spam@nowhere.mail>']
License: MIT
Platform: UNKNOWN
Classifier: Environment :: Web Environment
Classifier: Intended Audience :: Developers
Classifier: License :: OSI Approved :: MIT License
Classifier: Operating System :: OS Independent
Classifier: Programming Language :: Python :: 3.6
Classifier: Programming Language :: Python :: 3.7
Classifier: Programming Language :: Python :: 3.8
Classifier: Programming Language :: Python :: 3.9
Classifier: Programming Language :: Python :: 3.10
License-File: LICENSE
